<PAMDataset>
  <PAMRasterBand band="1">
    <Description>Layer_1</Description>
    <Metadata>
      <MDI key="LAYER_TYPE">athematic</MDI>
      <MDI key="STATISTICS_MAXIMUM">0.25288325548172</MDI>
      <MDI key="STATISTICS_MEAN">0.018990371511121</MDI>
      <MDI key="STATISTICS_MINIMUM">0</MDI>
      <MDI key="STATISTICS_STDDEV">0.04831307246494</MDI>
    </Metadata>
  </PAMRasterBand>
  <PAMRasterBand band="2">
    <Description>Layer_2</Description>
    <Metadata>
      <MDI key="LAYER_TYPE">athematic</MDI>
      <MDI key="STATISTICS_MAXIMUM">0.23271131515503</MDI>
      <MDI key="STATISTICS_MEAN">0.017185727460628</MDI>
      <MDI key="STATISTICS_MINIMUM">0</MDI>
      <MDI key="STATISTICS_STDDEV">0.043923517171527</MDI>
    </Metadata>
  </PAMRasterBand>
  <PAMRasterBand band="3">
    <Description>Layer_3</Description>
    <Metadata>
      <MDI key="LAYER_TYPE">athematic</MDI>
      <MDI key="STATISTICS_MAXIMUM">0.26560494303703</MDI>
      <MDI key="STATISTICS_MEAN">0.019152091606219</MDI>
      <MDI key="STATISTICS_MINIMUM">0</MDI>
      <MDI key="STATISTICS_STDDEV">0.048920046291457</MDI>
    </Metadata>
  </PAMRasterBand>
  <PAMRasterBand band="4">
    <Description>Layer_4</Description>
    <Metadata>
      <MDI key="LAYER_TYPE">athematic</MDI>
      <MDI key="STATISTICS_MAXIMUM">0.26201048493385</MDI>
      <MDI key="STATISTICS_MEAN">0.019891334352911</MDI>
      <MDI key="STATISTICS_MINIMUM">0</MDI>
      <MDI key="STATISTICS_STDDEV">0.049563468101381</MDI>
    </Metadata>
  </PAMRasterBand>
  <PAMRasterBand band="5">
    <Description>Layer_5</Description>
    <Metadata>
      <MDI key="LAYER_TYPE">athematic</MDI>
      <MDI key="STATISTICS_MAXIMUM">0.17478169500828</MDI>
      <MDI key="STATISTICS_MEAN">0.021897114264201</MDI>
      <MDI key="STATISTICS_MINIMUM">0</MDI>
      <MDI key="STATISTICS_STDDEV">0.053474585577733</MDI>
    </Metadata>
  </PAMRasterBand>
  <PAMRasterBand band="6">
    <Description>Layer_6</Description>
    <Metadata>
      <MDI key="LAYER_TYPE">athematic</MDI>
      <MDI key="STATISTICS_MAXIMUM">0.1716361194849</MDI>
      <MDI key="STATISTICS_MEAN">0.02102303342047</MDI>
      <MDI key="STATISTICS_MINIMUM">0</MDI>
      <MDI key="STATISTICS_STDDEV">0.051668357631142</MDI>
    </Metadata>
  </PAMRasterBand>
  <PAMRasterBand band="7">
    <Description>Layer_7</Description>
    <Metadata>
      <MDI key="LAYER_TYPE">athematic</MDI>
      <MDI key="STATISTICS_MAXIMUM">0.29098036885262</MDI>
      <MDI key="STATISTICS_MEAN">0.019359867557881</MDI>
      <MDI key="STATISTICS_MINIMUM">0</MDI>
      <MDI key="STATISTICS_STDDEV">0.050346596374675</MDI>
    </Metadata>
  </PAMRasterBand>
  <PAMRasterBand band="8">
    <Description>Layer_8</Description>
    <Metadata>
      <MDI key="LAYER_TYPE">athematic</MDI>
      <MDI key="STATISTICS_MAXIMUM">0.28009897470474</MDI>
      <MDI key="STATISTICS_MEAN">0.017620968946902</MDI>
      <MDI key="STATISTICS_MINIMUM">0</MDI>
      <MDI key="STATISTICS_STDDEV">0.047429324215631</MDI>
    </Metadata>
  </PAMRasterBand>
  <PAMRasterBand band="9">
    <Description>Layer_9</Description>
    <Metadata>
      <MDI key="LAYER_TYPE">athematic</MDI>
      <MDI key="STATISTICS_MAXIMUM">0.26168155670166</MDI>
      <MDI key="STATISTICS_MEAN">0.018342863388716</MDI>
      <MDI key="STATISTICS_MINIMUM">0</MDI>
      <MDI key="STATISTICS_STDDEV">0.047208846259244</MDI>
    </Metadata>
  </PAMRasterBand>
  <PAMRasterBand band="10">
    <Description>Layer_10</Description>
    <Metadata>
      <MDI key="LAYER_TYPE">athematic</MDI>
      <MDI key="STATISTICS_MAXIMUM">0.26496025919914</MDI>
      <MDI key="STATISTICS_MEAN">0.020272571171659</MDI>
      <MDI key="STATISTICS_MINIMUM">0</MDI>
      <MDI key="STATISTICS_STDDEV">0.051357143438958</MDI>
    </Metadata>
  </PAMRasterBand>
  <PAMRasterBand band="11">
    <Description>Layer_11</Description>
    <Metadata>
      <MDI key="LAYER_TYPE">athematic</MDI>
      <MDI key="STATISTICS_MAXIMUM">0.25453966856003</MDI>
      <MDI key="STATISTICS_MEAN">0.020652823123081</MDI>
      <MDI key="STATISTICS_MINIMUM">0</MDI>
      <MDI key="STATISTICS_STDDEV">0.051564204423763</MDI>
    </Metadata>
  </PAMRasterBand>
  <PAMRasterBand band="12">
    <Description>Layer_12</Description>
    <Metadata>
      <MDI key="LAYER_TYPE">athematic</MDI>
      <MDI key="STATISTICS_MAXIMUM">0.24942193925381</MDI>
      <MDI key="STATISTICS_MEAN">0.021945765379262</MDI>
      <MDI key="STATISTICS_MINIMUM">0</MDI>
      <MDI key="STATISTICS_STDDEV">0.053679714977976</MDI>
    </Metadata>
  </PAMRasterBand>
</PAMDataset>
